{"annotations": [{"id": 186861, "image_id": 28636, "category_id": 2, "bbox": [73, 276, 38.93333333333333, 37.54666666666667], "area": 1461.8168888888888, "segmentation": [], "iscrowd": 0}, {"id": 186862, "image_id": 28636, "category_id": 2, "bbox": [75, 276, 33.06666666666666, 34.98666666666667], "area": 1156.8924444444444, "segmentation": [], "iscrowd": 0}, {"id": 186865, "image_id": 28636, "category_id": 3, "bbox": [311, 271, 5.866666666666666, 34.98666666666667], "area": 205.25511111111112, "segmentation": [], "iscrowd": 0}, {"id": 186866, "image_id": 28636, "category_id": 3, "bbox": [355, 265, 6.933333333333334, 35.84], "area": 248.4906666666667, "segmentation": [], "iscrowd": 0}, {"id": 186867, "image_id": 28636, "category_id": 2, "bbox": [411, 253, 60.266666666666666, 48.64], "area": 2931.3706666666667, "segmentation": [], "iscrowd": 0}, {"id": 186868, "image_id": 28636, "category_id": 2, "bbox": [411, 254, 62.4, 48.64], "area": 3035.136, "segmentation": [], "iscrowd": 0}, {"id": 186869, "image_id": 28636, "category_id": 2, "bbox": [454, 225, 56.53333333333333, 78.50666666666667], "area": 4438.243555555556, "segmentation": [], "iscrowd": 0}], "image_name": "1478899978481068273_jpg.rf.uzkKXPFcEuTb7ad11DIE.jpg", "image_h": 512, "image_w": 512}